Metadata-Version: 2.1
Name: odoo12-addon-test-invader-payment
Version: 12.0.3.0.0
Summary: Test Invader payment
Home-page: https://github.com/shopinvader/odoo-shopinvader-payment
Author: Akretion
License: AGPL-3
Platform: UNKNOWN
Classifier: Programming Language :: Python
Classifier: Framework :: Odoo
Classifier: License :: OSI Approved :: GNU Affero General Public License v3
Requires-Python: >=3.5
Requires-Dist: odoo12-addon-invader-payment-manual
Requires-Dist: odoo12-addon-invader-payment-sips
Requires-Dist: odoo12-addon-invader-payment-stripe
Requires-Dist: odoo (<12.1dev,>=12.0a)
